LICENSE
README.md
setup.py
dds_cloudapi_sdk/__init__.py
dds_cloudapi_sdk/client.py
dds_cloudapi_sdk/config.py
dds_cloudapi_sdk/image_resizer.py
dds_cloudapi_sdk/rle_util.py
dds_cloudapi_sdk/visualization_util.py
dds_cloudapi_sdk.egg-info/PKG-INFO
dds_cloudapi_sdk.egg-info/SOURCES.txt
dds_cloudapi_sdk.egg-info/dependency_links.txt
dds_cloudapi_sdk.egg-info/requires.txt
dds_cloudapi_sdk.egg-info/top_level.txt
dds_cloudapi_sdk/tasks/__init__.py
dds_cloudapi_sdk/tasks/base.py
dds_cloudapi_sdk/tasks/v2_task.py
test/test.py