Metadata-Version: 2.1
Name: dds-cloudapi-sdk
Version: 0.5.2
Summary: The SDK for calling deepdataspace cloud API.
Home-page: https://github.com/deepdataspace/dds-cloudapi-sdk
Author: cvr@idea
Classifier: Development Status :: 4 - Beta
Classifier: Topic :: Scientific/Engineering :: Artificial Intelligence
Classifier: Topic :: Scientific/Engineering :: Image Recognition
Classifier: Topic :: Scientific/Engineering :: Visualization
Classifier: Operating System :: MacOS :: MacOS X
Classifier: Operating System :: POSIX :: Linux
Classifier: Operating System :: Microsoft :: Windows
Classifier: Programming Language :: Python :: 3
Classifier: Programming Language :: Python :: 3.8
Classifier: Programming Language :: Python :: 3.9
Classifier: Programming Language :: Python :: 3.10
License-File: LICENSE
Requires-Dist: numpy>=1.24.4
Requires-Dist: pillow>=10.2.0
Requires-Dist: requests>=2.31.0
Requires-Dist: sentry_sdk>=2.28.0
Requires-Dist: opencv-python
